MANIFEST.in
README.rst
setup.py
pagecache/__init__.py
pagecache/pagecache.py
pagecache/test_pagecache.py
pagecache.egg-info/PKG-INFO
pagecache.egg-info/SOURCES.txt
pagecache.egg-info/dependency_links.txt
pagecache.egg-info/not-zip-safe
pagecache.egg-info/requires.txt
pagecache.egg-info/top_level.txt