Metadata-Version: 1.0
Name: pagecache
Version: 0.1.1
Summary: Page caching WSGI middleware
Home-page: http://github.com/abiczo/pagecache
Author: Andras Biczo
Author-email: abiczo@gmail.com
License: MIT
Keywords: cache wsgi
Platform: UNKNOWN
Classifier: Development Status :: 3 - Alpha
Classifier: Environment :: Web Environment
Classifier: Intended Audience :: Developers
Classifier: License :: OSI Approved :: MIT License
Classifier: Programming Language :: Python
Classifier: Topic :: Internet :: WWW/HTTP :: WSGI :: Middleware
Classifier: Topic :: Software Development :: Libraries :: Python Modules
